skill_metrics/UserDict.py
skill_metrics/__init__.py
skill_metrics/add_legend.py
skill_metrics/bias.py
skill_metrics/bias_percent.py
skill_metrics/brier_score.py
skill_metrics/centered_rms_dev.py
skill_metrics/check_duplicate_stats.py
skill_metrics/check_on_off.py
skill_metrics/check_taylor_stats.py
skill_metrics/error_check_stats.py
skill_metrics/get_axis_tick_label.py
skill_metrics/get_default_markers.py
skill_metrics/get_from_dict_or_default.py
skill_metrics/get_single_markers.py
skill_metrics/get_target_diagram_axes.py
skill_metrics/get_target_diagram_options.py
skill_metrics/get_taylor_diagram_axes.py
skill_metrics/get_taylor_diagram_options.py
skill_metrics/kling_gupta_eff09.py
skill_metrics/kling_gupta_eff12.py
skill_metrics/nash_sutcliffe_eff.py
skill_metrics/nse.py
skill_metrics/overlay_target_diagram_circles.py
skill_metrics/overlay_taylor_diagram_circles.py
skill_metrics/overlay_taylor_diagram_lines.py
skill_metrics/plot_pattern_diagram_colorbar.py
skill_metrics/plot_pattern_diagram_markers.py
skill_metrics/plot_target_axes.py
skill_metrics/plot_taylor_axes.py
skill_metrics/plot_taylor_obs.py
skill_metrics/report_duplicate_stats.py
skill_metrics/rmsd.py
skill_metrics/save_figures.py
skill_metrics/skill_score_brier.py
skill_metrics/skill_score_murphy.py
skill_metrics/target_diagram.py
skill_metrics/target_statistics.py
skill_metrics/taylor_diagram.py
skill_metrics/taylor_statistics.py
skill_metrics/use_sci_notation.py
skill_metrics/utils.py
skill_metrics/write_stats.py
skill_metrics/write_target_stats.py
skill_metrics/write_taylor_stats.py
SkillMetrics-1.2.4.dist-info/LICENSE.txt
SkillMetrics-1.2.4.dist-info/METADATA
SkillMetrics-1.2.4.dist-info/WHEEL
SkillMetrics-1.2.4.dist-info/top_level.txt
SkillMetrics-1.2.4.dist-info/RECORD
