Metadata-Version: 2.1
Name: SkillMetrics
Version: 1.2.4
Summary: A Python library for calculating and displaying the skill of model predictions against observations.
Home-page: https://github.com/PeterRochford/SkillMetrics/tree/master
Author: Peter Rochford
Author-email: rochford.peter1@gmail.com
Classifier: Development Status :: 4 - Beta
Classifier: Intended Audience :: Developers
Classifier: License :: OSI Approved :: GNU General Public License v3 (GPLv3)
Classifier: Programming Language :: Python :: 3.11
License-File: LICENSE.txt
Requires-Dist: matplotlib
Requires-Dist: numpy
Requires-Dist: pandas
Requires-Dist: xlsxwriter
